ASHReports/__init__.py
ASHReports/__main__.pyw
ASHReports/init_functions.dll
ASHReports/report_log.exe
ASHReports/ui_form.py
ashreports-0.3.4.dist-info/METADATA
ashreports-0.3.4.dist-info/WHEEL
ashreports-0.3.4.dist-info/licenses/LICENCE.txt
ashreports-0.3.4.dist-info/RECORD
