Metadata-Version: 2.4
Name: ASHReports
Version: 0.3.4
Summary: Weekly Report for ASH, made by Tanmoy Sarkar
Project-URL: Homepage, https://github.com/sarkar-tanmoy/
Project-URL: Repository, https://github.com/sarkar-tanmoy/
Author-email: Tanmoy Sarkar <tanmoy.apparel@gmail.com>
Maintainer-email: Tanmoy Sarkar <tanmoy.apparel@gmail.com>
License-Expression: MIT AND (Apache-2.0 OR BSD-2-Clause)
License-File: LICENCE.txt
Keywords: ASHReport,ash reports
Classifier: Development Status :: 5 - Production/Stable
Classifier: Programming Language :: Python :: 3
Requires-Python: >=3.11
Requires-Dist: ashc-v3
Requires-Dist: fastexcel>=0.14.0
Requires-Dist: nuitka>=2.7.11
Requires-Dist: numpy>=2.2.6
Requires-Dist: polars<=1.35.2
Requires-Dist: pyarrow>=20.0.0
Requires-Dist: pyside6==6.9.1
Requires-Dist: xlwings>=0.33.15
